requests_ip_rotator/__init__.py
requests_ip_rotator/ip_rotator.py
requests_ip_rotator-1.0.14.dist-info/LICENSE
requests_ip_rotator-1.0.14.dist-info/METADATA
requests_ip_rotator-1.0.14.dist-info/WHEEL
requests_ip_rotator-1.0.14.dist-info/top_level.txt
requests_ip_rotator-1.0.14.dist-info/RECORD
